{
  "project_info": {
    "project_number": "586833734162",
    "firebase_url": "https://art-on-the-move-1d505-default-rtdb.europe-west1.firebasedatabase.app",
    "project_id": "art-on-the-move-1d505",
    "storage_bucket": "art-on-the-move-1d505.appspot.com"
  },
  "client": [
    {
      "client_info": {
        "mobilesdk_app_id": "1:586833734162:android:df6d2886e817cd6dfd86cb",
        "android_client_info": {
          "package_name": "com.anyitrecruitment"
        }
      },
      "oauth_client": [
        {
          "client_id": "586833734162-0str891jaugok5dr8lifq6dumghmvps8.apps.googleusercontent.com",
          "client_type": 3
        }
      ],
      "api_key": [
        {
          "current_key": "AIzaSyCaD209TnqkPqx7fDgykLICVGaIQI4_0w4"
        }
      ],
      "services": {
        "appinvite_service": {
          "other_platform_oauth_client": [
            {
              "client_id": "586833734162-0str891jaugok5dr8lifq6dumghmvps8.apps.googleusercontent.com",
              "client_type": 3
            }
          ]
        }
      }
    }
  ],
  "configuration_version": "1"
}